pulumi_hcloud/__init__.py
pulumi_hcloud/_inputs.py
pulumi_hcloud/_utilities.py
pulumi_hcloud/certificate.py
pulumi_hcloud/firewall.py
pulumi_hcloud/firewall_attachment.py
pulumi_hcloud/floating_ip.py
pulumi_hcloud/floating_ip_assignment.py
pulumi_hcloud/get_certificate.py
pulumi_hcloud/get_certificates.py
pulumi_hcloud/get_datacenter.py
pulumi_hcloud/get_datacenters.py
pulumi_hcloud/get_firewall.py
pulumi_hcloud/get_firewalls.py
pulumi_hcloud/get_floating_ip.py
pulumi_hcloud/get_floating_ips.py
pulumi_hcloud/get_image.py
pulumi_hcloud/get_images.py
pulumi_hcloud/get_load_balancer.py
pulumi_hcloud/get_load_balancer_type.py
pulumi_hcloud/get_load_balancer_types.py
pulumi_hcloud/get_load_balancers.py
pulumi_hcloud/get_location.py
pulumi_hcloud/get_locations.py
pulumi_hcloud/get_network.py
pulumi_hcloud/get_networks.py
pulumi_hcloud/get_placement_group.py
pulumi_hcloud/get_placement_groups.py
pulumi_hcloud/get_primary_ip.py
pulumi_hcloud/get_primary_ips.py
pulumi_hcloud/get_server.py
pulumi_hcloud/get_server_type.py
pulumi_hcloud/get_server_types.py
pulumi_hcloud/get_servers.py
pulumi_hcloud/get_ssh_key.py
pulumi_hcloud/get_ssh_keys.py
pulumi_hcloud/get_storage_box.py
pulumi_hcloud/get_storage_box_snapshot.py
pulumi_hcloud/get_storage_box_snapshots.py
pulumi_hcloud/get_storage_box_subaccount.py
pulumi_hcloud/get_storage_box_subaccounts.py
pulumi_hcloud/get_storage_box_type.py
pulumi_hcloud/get_storage_box_types.py
pulumi_hcloud/get_storage_boxes.py
pulumi_hcloud/get_volume.py
pulumi_hcloud/get_volumes.py
pulumi_hcloud/get_zone.py
pulumi_hcloud/get_zone_rrset.py
pulumi_hcloud/get_zone_rrsets.py
pulumi_hcloud/get_zones.py
pulumi_hcloud/load_balancer.py
pulumi_hcloud/load_balancer_network.py
pulumi_hcloud/load_balancer_service.py
pulumi_hcloud/load_balancer_target.py
pulumi_hcloud/managed_certificate.py
pulumi_hcloud/network.py
pulumi_hcloud/network_route.py
pulumi_hcloud/network_subnet.py
pulumi_hcloud/outputs.py
pulumi_hcloud/placement_group.py
pulumi_hcloud-1.32.0.dist-info/METADATA
pulumi_hcloud-1.32.0.dist-info/WHEEL
pulumi_hcloud-1.32.0.dist-info/top_level.txt
pulumi_hcloud-1.32.0.dist-info/RECORD
